[
    {
        "tarea": "ASDAS",
        "fecha": "",
        "completada": "Pendiente",
        "correo_enviado": false,
        "tiempo": "",
        "prioridad": "No urgente"
    },
    {
        "tarea": "ASD",
        "fecha": "",
        "completada": "Pendiente",
        "correo_enviado": false,
        "tiempo": "3 h 5m",
        "prioridad": "Muy urgente"
    },
    {
        "tarea": "SADASD",
        "fecha": "",
        "completada": "Pendiente",
        "correo_enviado": false,
        "tiempo": "2 h 10m",
        "prioridad": "No urgente"
    },
    {
        "tarea": "asdasd",
        "fecha": "22/2/25",
        "completada": "Pendiente",
        "correo_enviado": false,
        "tiempo": "",
        "prioridad": ""
    },
    {
        "tarea": "sadasdasd",
        "fecha": "",
        "completada": "Pendiente",
        "correo_enviado": false,
        "tiempo": "",
        "prioridad": ""
    },
    {
        "tarea": "sada",
        "fecha": "",
        "completada": "Pendiente",
        "correo_enviado": false,
        "tiempo": "",
        "prioridad": ""
    }
]